[
    {
        "id": 1,
        "name": "Sticker de música",
        "tags": [
            "stickers",
            "music"
        ],
        "category": "series",
        "img": "../assets/RM3.png",
        "price": 1.99,
        "sale": true,
        "description": "Rítmico sticker con diseño de música"
    },
    {
        "id": 2,
        "name": "Sticker de música",
        "tags": [
            "stickers",
            "music"
        ],
        "category": "series",
        "img": "../assets/RM4.png",
        "price": 1.99,
        "sale": true,
        "description": "Rítmico sticker con diseño de música"
    },
    {
        "id": 3,
        "name": "Sticker de música",
        "tags": [
            "stickers",
            "music"
        ],
        "category": "series",
        "img": "../assets/RM5.png",
        "price": 1.99,
        "sale": true,
        "description": "Rítmico sticker con diseño de música"
    },
    {
        "id": 4,
        "name": "Sticker de gatito",
        "tags": [
            "stickers",
            "cute"
        ],
        "category": "Música",
        "img": "../assets/AM1.png",
        "price": 2.99,
        "sale": false,
        "description": "Adorable sticker con diseño de gatito"
    },
    {
        "id": 5,
        "name": "Sticker de emoji",
        "tags": [
            "stickers",
            "funny"
        ],
        "category": "Música",
        "img": "../assets/AM2.png",
        "price": 1.99,
        "sale": true,
        "description": "Divertido sticker con diseño de emoji"
    },
    {
        "id": 6,
        "name": "Sticker de calavera",
        "tags": [
            "stickers",
            "cool"
        ],
        "category": "Música",
        "img": "../assets/AM3.png",
        "price": 3.49,
        "sale": false,
        "description": "Sticker genial con diseño de calavera"
    },
    {
        "id": 7,
        "name": "Sticker de corazón",
        "tags": [
            "stickers",
            "love"
        ],
        "category": "Música",
        "img": "../assets/AM4.png",
        "price": 2.99,
        "sale": false,
        "description": "Hermoso sticker con diseño de corazón"
    },
    {
        "id": 8,
        "name": "Sticker de estrella",
        "tags": [
            "stickers",
            "sparkle"
        ],
        "category": "Música",
        "img": "../assets/AM5.png",
        "price": 1.99,
        "sale": true,
        "description": "Brillante sticker con diseño de estrella"
    },
    {
        "id": 9,
        "name": "Sticker de fuego",
        "tags": [
            "stickers",
            "hot"
        ],
        "category": "Música",
        "img": "../assets/BB1.png",
        "price": 3.49,
        "sale": false,
        "description": "Increíble sticker con diseño de fuego"
    },
    {
        "id": 10,
        "name": "Sticker de fuego",
        "tags": [
            "stickers",
            "hot"
        ],
        "category": "Música",
        "img": "../assets/BB2.png",
        "price": 3.49,
        "sale": false,
        "description": "Increíble sticker con diseño de fuego"
    },
    {
        "id": 11,
        "name": "Sticker de fuego",
        "tags": [
            "stickers",
            "hot"
        ],
        "category": "Música",
        "img": "../assets/BB3.png",
        "price": 3.49,
        "sale": false,
        "description": "Increíble sticker con diseño de fuego"
    },
    {
        "id": 12,
        "name": "Sticker de fuego",
        "tags": [
            "stickers",
            "hot"
        ],
        "category": "Música",
        "img": "../assets/BB4.png",
        "price": 3.49,
        "sale": false,
        "description": "Increíble sticker con diseño de fuego"
    },
    {
        "id": 13,
        "name": "Sticker de fuego",
        "tags": [
            "stickers",
            "hot"
        ],
        "category": "Música",
        "img": "../assets/BB5.png",
        "price": 3.49,
        "sale": false,
        "description": "Increíble sticker con diseño de fuego"
    },
    {
        "id": 14,
        "name": "Sticker de arcoíris",
        "tags": [
            "stickers",
            "colorful"
        ],
        "category": "anime",
        "img": "../assets/CSM1.png",
        "price": 2.99,
        "sale": false,
        "description": "Alegre sticker con diseño de arcoíris"
    },
    {
        "id": 15,
        "name": "Sticker de arcoíris",
        "tags": [
            "stickers",
            "colorful"
        ],
        "category": "anime",
        "img": "../assets/CSM1.png",
        "price": 2.99,
        "sale": false,
        "description": "Alegre sticker con diseño de arcoíris"
    },
    {
        "id": 16,
        "name": "Sticker de arcoíris",
        "tags": [
            "stickers",
            "colorful"
        ],
        "category": "anime",
        "img": "../assets/CSM2.png",
        "price": 2.99,
        "sale": false,
        "description": "Alegre sticker con diseño de arcoíris"
    },
    {
        "id": 17,
        "name": "Sticker de arcoíris",
        "tags": [
            "stickers",
            "colorful"
        ],
        "category": "anime",
        "img": "../assets/CSM3.png",
        "price": 2.99,
        "sale": false,
        "description": "Alegre sticker con diseño de arcoíris"
    },
    {
        "id": 18,
        "name": "Sticker de arcoíris",
        "tags": [
            "stickers",
            "colorful"
        ],
        "category": "anime",
        "img": "../assets/CSM4.png",
        "price": 2.99,
        "sale": false,
        "description": "Alegre sticker con diseño de arcoíris"
    },
    {
        "id": 19,
        "name": "Sticker de arcoíris",
        "tags": [
            "stickers",
            "colorful"
        ],
        "category": "anime",
        "img": "../assets/CSM5.png",
        "price": 2.99,
        "sale": false,
        "description": "Alegre sticker con diseño de arcoíris"
    },
    {
        "id": 20,
        "name": "Sticker de música",
        "tags": [
            "stickers",
            "music"
        ],
        "category": "series",
        "img": "../assets/RM1.png",
        "price": 1.99,
        "sale": true,
        "description": "Rítmico sticker con diseño de música"
    },
    {
        "id": 21,
        "name": "Sticker de música",
        "tags": [
            "stickers",
            "music"
        ],
        "category": "series",
        "img": "../assets/RM2.png",
        "price": 1.99,
        "sale": true,
        "description": "Rítmico sticker con diseño de música"
    }
]
